storysmith/__init__.py
storysmith-0.1.1.dist-info/METADATA
storysmith-0.1.1.dist-info/WHEEL
storysmith-0.1.1.dist-info/licenses/LICENSE
storysmith-0.1.1.dist-info/RECORD
