Metadata-Version: 2.4
Name: storysmith
Version: 0.1.1
Summary: A storytelling toolkit
Project-URL: Homepage, https://github.com/story-smith/storysmith
Project-URL: Repository, https://github.com/story-smith/storysmith
Project-URL: Issues, https://github.com/story-smith/storysmith/issues
Author-email: Kotaro Nishigori <kotaro.nishigori@gmail.com>
License: MIT
License-File: LICENSE
Requires-Python: >=3.13
